intelelm/__init__.py
intelelm/data/cls/Arrhythmia.csv
intelelm/data/cls/Blood.csv
intelelm/data/cls/BreastCancer.csv
intelelm/data/cls/BreastEW.csv
intelelm/data/cls/CongressEW.csv
intelelm/data/cls/Digits.csv
intelelm/data/cls/Glass.csv
intelelm/data/cls/HeartEW.csv
intelelm/data/cls/Hill-valley.csv
intelelm/data/cls/Horse.csv
intelelm/data/cls/Ionosphere.csv
intelelm/data/cls/Iris.csv
intelelm/data/cls/Lymphography.csv
intelelm/data/cls/Madelon.csv
intelelm/data/cls/Monk1.csv
intelelm/data/cls/Monk2.csv
intelelm/data/cls/Monk3.csv
intelelm/data/cls/Sonar.csv
intelelm/data/cls/Soybean-small.csv
intelelm/data/cls/SpectEW.csv
intelelm/data/cls/Tic-tac-toe.csv
intelelm/data/cls/Vowel.csv
intelelm/data/cls/WaveformEW.csv
intelelm/data/cls/Wine.csv
intelelm/data/cls/Zoo.csv
intelelm/data/cls/aggregation.csv
intelelm/data/cls/aniso.csv
intelelm/data/cls/appendicitis.csv
intelelm/data/cls/balance.csv
intelelm/data/cls/banknote.csv
intelelm/data/cls/blobs.csv
intelelm/data/cls/circles.csv
intelelm/data/cls/diagnosis_II.csv
intelelm/data/cls/ecoli.csv
intelelm/data/cls/flame.csv
intelelm/data/cls/heart.csv
intelelm/data/cls/jain.csv
intelelm/data/cls/liver.csv
intelelm/data/cls/moons.csv
intelelm/data/cls/mouse.csv
intelelm/data/cls/pathbased.csv
intelelm/data/cls/seeds.csv
intelelm/data/cls/smiley.csv
intelelm/data/cls/varied.csv
intelelm/data/cls/vary-density.csv
intelelm/data/cls/vertebral2.csv
intelelm/data/cls/wdbc.csv
intelelm/data/reg/boston-housing.csv
intelelm/data/reg/computer-hardware.csv
intelelm/data/reg/diabetes.csv
intelelm/data/reg/gauss-100-20.csv
intelelm/data/reg/gauss-50-12.csv
intelelm/data/reg/gauss-75-17.csv
intelelm/data/reg/linnerud.csv
intelelm/model/__init__.py
intelelm/model/automated_comparator.py
intelelm/model/automated_tuner.py
intelelm/model/base_elm.py
intelelm/model/mha_elm.py
intelelm/model/standard_elm.py
intelelm/utils/__init__.py
intelelm/utils/activation.py
intelelm/utils/data_loader.py
intelelm/utils/encoder.py
intelelm-1.3.0.dist-info/licenses/LICENSE
intelelm-1.3.0.dist-info/METADATA
intelelm-1.3.0.dist-info/WHEEL
intelelm-1.3.0.dist-info/top_level.txt
intelelm-1.3.0.dist-info/RECORD
